{"jumlah_ruang_kelas": 6, "daya_listrik": 900, "sarana_prasarana": {"sanitasi": {"siswa": {"rusak_ringan": 1, "baik": 0, "rusak_sedang": 0}, "guru": {"rusak_ringan": 2, "baik": 0, "rusak_sedang": 0}}, "ruang_kelas": {"rusak_berat": {"bukan_milik": 0, "milik": 0}, "rusak_ringan": {"bukan_milik": 0, "milik": 6}, "baik": {"bukan_milik": 0, "milik": 0}, "rusak_sedang": {"bukan_milik": 0, "milik": 0}}, "laboratorium": {"ipa": {"rusak_ringan": 0, "baik": 0, "rusak_sedang": 0}, "kimia": {"rusak_ringan": 0, "baik": 0, "rusak_sedang": 0}, "ips": {"rusak_ringan": 0, "baik": 0, "rusak_sedang": 0}, "biologi": {"rusak_ringan": 0, "baik": 0, "rusak_sedang": 0}, "bahasa": {"rusak_ringan": 0, "baik": 0, "rusak_sedang": 0}, "fisika": {"rusak_ringan": 0, "baik": 0, "rusak_sedang": 0}, "komputer": {"rusak_ringan": 0, "baik": 0, "rusak_sedang": 0}}, "prasarana_lainnya": [{"nama": "Dapur                          (Lainnya)", "keterangan": 0}, {"nama": "Gudang                         (Gudang)", "keterangan": 0}, {"nama": "Perumahan 1                    (Rumah Dinas Kepala Sekolah)", "keterangan": 0}, {"nama": "Perumahan 2 (Rumah Dinas Kepala Sekolah)", "keterangan": 0}, {"nama": "Perumahan 3                    (Rumah Dinas Guru)", "keterangan": 0}, {"nama": "Perumahan 4                    (Rumah Dinas Guru)", "keterangan": 0}, {"nama": "Perumahan 5                    (Rumah Penjaga Sekolah)", "keterangan": 0}, {"nama": "Ruang Guru (Ruang Guru)", "keterangan": 0}, {"nama": "Ruang Kepala Sekolah (Ruang Kepala Sekolah)", "keterangan": 0}], "perpustakaan": {"rusak_berat": 0, "rusak_ringan": 1, "baik": 0, "rusak_sedang": 0}}, "luas_tanah": 0, "akses_internet": true, "jumlah_siswa_laki_laki": 73, "nilai_ujian_nasional": {}, "alamat": "Borong jatie, Jalanjang, Kec. Gantarang, Kab. Bulukumba Prop. Sulawesi Selatan", "kurikulum": "K-13", "nilai_akreditasi": [{"standar_sarana_prasarana": 91, "akreditasi": " B", "standar_isi": 80, "nilai_akhir": 84, "tahun": 2016, "standar_penilaian": 88, "standar_pengelolaan": 81, "standar_kelulusan": 81, "keterangan": " ", "standar_tenaga_pendidik": 81, "standar_pembiayaan": 93, "standar_proses": 81}], "npsn_sekolah": "40312706", "guru": {"status": {"gty": 0, "pns": 7, "gtt": 0, "honor": 2}, "ijazah": {"s1_atau_lebih": 5, "kurang_dari_s1": 3, "data_kosong": 1}, "sertifikasi": {"belum_sertifikasi": 5, "sertifikasi": 4}, "daftar": [{"jenis_kelamin": "P", "nama": "Hasminah", "nuptk": "95637386383XXXXX"}, {"jenis_kelamin": "P", "nama": "Hawise", "nuptk": "70397396403XXXXX"}, {"jenis_kelamin": "P", "nama": "Risma Asma", "nuptk": "31607656672XXXXX"}, {"jenis_kelamin": "P", "nama": "SUBAEDAH", "nuptk": "72517406423XXXXX"}, {"jenis_kelamin": "P", "nama": "NUR HAERAWATI", "nuptk": "78557486503XXXXX"}, {"jenis_kelamin": "P", "nama": "Nurwati", "nuptk": "67557556573XXXXX"}, {"jenis_kelamin": "P", "nama": "Anugrah", "nuptk": "13347656672XXXXX"}, {"jenis_kelamin": "L", "nama": "RAJAMUDDING", "nuptk": "84427366402XXXXX"}, {"jenis_kelamin": "L", "nama": "Amirullah", "nuptk": "15477636651XXXXX"}], "jenis_kelamin": {"laki-laki": 2, "perempuan": 7}, "golongan": {"I": 2, "II": 1, "III": 2, "IV": 4}, "umur": {"lte30": 2, "36-40": 1, "41-45": 0, "51-55": 1, "46-50": 1, "gt55": 3, "31-35": 1}}, "semester_aktif": "2017/2018-1", "program_pembangunan_bantuan": {"rehab": [], "pip": [{"tahun": 2015, "jumlah_penerima": 20}], "vokasi": [], "usb": [], "rkb": [], "tik": [], "revitalisasi": [], "sanitasi": [], "bos": [{"tahun": 2013, "jumlah_siswa": 125}], "sarana_kesenian": []}, "jumlah_perpustakaan": 1, "waktu_penyelenggaraan": "Pagi", "jumlah_rombongan_belajar": 6, "manajemen_berbasis_sekolah": false, "jumlah_siswa_perempuan": 68, "jumlah_guru": 9, "rombongan_belajar": {"tingkat": {"1": 1, "3": 1, "2": 1, "5": 1, "4": 1, "6": 1}}, "sanitasi_siswa": 1, "detail_sekolah": {"operator": "AMIRULLAH, S.Pd", "telepon": "-", "akreditasi": "-", "kepala_sekolah": "SITTI SALMAH", "email": "sdn297matekko@yahoo.co.id"}, "sumber_listrik": true, "tenaga_kependidikan": {"status": {"pns": 0, "honor": 0}, "ijazah": {"s1_atau_lebih": 0, "kurang_dari_s1": 0, "data_kosong": 0}, "sertifikasi": {}, "daftar": [], "jenis_kelamin": {"laki-laki": 0, "perempuan": 0}, "golongan": {"I": 0, "II": 0, "III": 0, "IV": 0}, "umur": {"lte30": 0, "36-40": 0, "41-45": 0, "51-55": 0, "46-50": 0, "gt55": 0, "31-35": 0}}, "jumlah_laboratorium": 0, "kecamatan": "Kec. Gantarang", "proses_pembelajaran": {"rasio_siswa_ruang_kelas": 24, "presentasi_guru_sertifikasi": 44.44, "rasio_siswa_guru": 16, "presentasi_guru_pns": 77.78, "rasio_siswa_rombel": 24, "presentasi_guru_kelas_layak": 100, "presentasi_guru_kualifikasi": 55.56}, "nama_sekolah": "SD NEGERI 297 MATEKKO", "prestasi_dan_penghargaan": {"guru_dan_tpk": [], "siswa": []}, "siswa": {"siswa_mengulang": {"siswa_mengulang_umur": {"gt12": 0, "lt7": 0, "7-12": 6}, "siswa_mengulang_jenis_kelamin": {"laki-laki": 3, "perempuan": 3}, "siswa_mengulang_tingkat": {"1": 1, "3": 2, "2": 3, "5": 0, "4": 0, "6": 0}}, "siswa_lulus": {"lulusan_umur": {"gt12": 13, "lt7": 0, "7-12": 9}, "lulusan_jenisKelamin": {"laki-laki": 10, "perempuan": 12}}, "siswa_baru": {"siswa_baru_umur": {"gt12": 0, "lt7": 8, "7-12": 17}, "siswa_baru_jenis_kelamin": {"laki-laki": 15, "perempuan": 10}}, "siswa": {"siswa_tingkat": {"1": 25, "3": 33, "2": 20, "5": 14, "4": 27, "6": 22}, "siswa_jenis_kelamin": {"laki-laki": 73, "perempuan": 68}, "siswa_agama": {"katholik": 0, "lainnya": 0, "hindu": 0, "islam": 141, "budha": 0, "kong_hu_chu": 0, "kristen": 0}, "siswa_umur": {"gt12": 4, "lt7": 8, "7-12": 129}}}}